EnsembleBench/__init__.py
EnsembleBench/diversityMetrics.py
EnsembleBench/groupMetrics.py
EnsembleBench/teamSelection.py
EnsembleBench-0.0.0.1.dist-info/METADATA
EnsembleBench-0.0.0.1.dist-info/WHEEL
EnsembleBench-0.0.0.1.dist-info/top_level.txt
EnsembleBench-0.0.0.1.dist-info/RECORD
