Metadata-Version: 2.1
Name: EnsembleBench
Version: 0.0.0.1
Summary: A set of tools for building good ensemble model teams in machine learning.
Home-page: https://github.com/git-disl/EnsembleBench
Author: Yanzhao Wu
Author-email: yanzhaowumail@gmail.com
License: UNKNOWN
Download-URL: https://github.com/git-disl/EnsembleBench/archive/master.zip
Keywords: ENSEMBLE,INFERENCE,MACHINE LEARNING
Platform: UNKNOWN
Classifier: Development Status :: 3 - Alpha
Classifier: Intended Audience :: Developers
Classifier: Intended Audience :: Science/Research
Classifier: Programming Language :: Python :: 2.7
Classifier: Programming Language :: Python :: 3
Classifier: Programming Language :: Python :: 3.4
Classifier: Programming Language :: Python :: 3.5
Classifier: Programming Language :: Python :: 3.6
Requires-Dist: numpy
Requires-Dist: matplotlib
Requires-Dist: scikit-learn
